MANIFEST.in
README.md
setup.py
ipyrmd/__init__.py
ipyrmd/ipyrmd.py
ipyrmd.egg-info/PKG-INFO
ipyrmd.egg-info/SOURCES.txt
ipyrmd.egg-info/dependency_links.txt
ipyrmd.egg-info/requires.txt
ipyrmd.egg-info/top_level.txt
scripts/ipyrmd