Metadata-Version: 1.1
Name: ipyrmd
Version: 0.4.3
Summary: Convert between IPython/Jupyter notebooks and RMarkdown
Home-page: https://github.com/chronitis/ipyrmd
Author: Gordon Ball
Author-email: gordon@chronitis.net
License: MIT
Keywords: ipython jupyter irkernel rmarkdown ipynb
Platform: UNKNOWN
Classifier: Development Status :: 4 - Beta
Classifier: Intended Audience :: Developers
Classifier: Intended Audience :: Science/Research
Classifier: License :: OSI Approved :: MIT License
Classifier: Programming Language :: Python :: 3
Classifier: Environment :: Console
Classifier: Framework :: IPython
Classifier: Topic :: Scientific/Engineering
Classifier: Topic :: Utilities
